alibabacloud_green20220926/__init__.py
alibabacloud_green20220926/client.py
alibabacloud_green20220926/models/__init__.py
alibabacloud_green20220926/models/_add_answer_sample_request.py
alibabacloud_green20220926/models/_add_answer_sample_response.py
alibabacloud_green20220926/models/_add_answer_sample_response_body.py
alibabacloud_green20220926/models/_add_image_lib_request.py
alibabacloud_green20220926/models/_add_image_lib_response.py
alibabacloud_green20220926/models/_add_image_lib_response_body.py
alibabacloud_green20220926/models/_add_images_2lib_request.py
alibabacloud_green20220926/models/_add_images_2lib_response.py
alibabacloud_green20220926/models/_add_images_2lib_response_body.py
alibabacloud_green20220926/models/_add_keyword_lib_request.py
alibabacloud_green20220926/models/_add_keyword_lib_response.py
alibabacloud_green20220926/models/_add_keyword_lib_response_body.py
alibabacloud_green20220926/models/_add_keywords_request.py
alibabacloud_green20220926/models/_add_keywords_response.py
alibabacloud_green20220926/models/_add_keywords_response_body.py
alibabacloud_green20220926/models/_add_keywords_to_lib_request.py
alibabacloud_green20220926/models/_add_keywords_to_lib_response.py
alibabacloud_green20220926/models/_add_keywords_to_lib_response_body.py
alibabacloud_green20220926/models/_cancel_stock_oss_check_task_request.py
alibabacloud_green20220926/models/_cancel_stock_oss_check_task_response.py
alibabacloud_green20220926/models/_cancel_stock_oss_check_task_response_body.py
alibabacloud_green20220926/models/_config_bucket_prefix_filter_config_value.py
alibabacloud_green20220926/models/_copy_service_config_request.py
alibabacloud_green20220926/models/_copy_service_config_response.py
alibabacloud_green20220926/models/_copy_service_config_response_body.py
alibabacloud_green20220926/models/_creat_stock_oss_check_task_request.py
alibabacloud_green20220926/models/_creat_stock_oss_check_task_response.py
alibabacloud_green20220926-1.5.6.dist-info/LICENSE
alibabacloud_green20220926-1.5.6.dist-info/METADATA
alibabacloud_green20220926-1.5.6.dist-info/WHEEL
alibabacloud_green20220926-1.5.6.dist-info/top_level.txt
alibabacloud_green20220926-1.5.6.dist-info/RECORD
